[{"values": [{"date": {"year": 2018, "month": 1}, "value": 100.0}, {"date": {"year": 2018, "month": 2}, "value": 99.29146554680474}, {"date": {"year": 2018, "month": 3}, "value": 99.51658262066628}, {"date": {"year": 2018, "month": 4}, "value": 100.20840060598309}, {"date": {"year": 2018, "month": 5}, "value": 100.50846412540996}, {"date": {"year": 2018, "month": 6}, "value": 99.6826188037604}, {"date": {"year": 2018, "month": 7}, "value": 99.92993580008344}, {"date": {"year": 2018, "month": 8}, "value": 99.90019612359063}, {"date": {"year": 2018, "month": 9}, "value": 100.08737514639444}, {"date": {"year": 2018, "month": 10}, "value": 100.18809861355487}, {"date": {"year": 2018, "month": 11}, "value": 100.61097828972439}, {"date": {"year": 2018, "month": 12}, "value": 100.85560022520467}, {"date": {"year": 2019, "month": 1}, "value": 101.06439290176984}, {"date": {"year": 2019, "month": 2}, "value": 101.5537265997432}, {"date": {"year": 2019, "month": 3}, "value": 101.53538548280982}, {"date": {"year": 2019, "month": 4}, "value": 101.34053796486366}, {"date": {"year": 2019, "month": 5}, "value": 100.8248462214024}, {"date": {"year": 2019, "month": 6}, "value": 100.64413373310784}, {"date": {"year": 2019, "month": 7}, "value": 101.61377530940646}, {"date": {"year": 2019, "month": 8}, "value": 102.99090290315831}, {"date": {"year": 2019, "month": 9}, "value": 104.53035357722837}, {"date": {"year": 2019, "month": 10}, "value": 105.21644539014835}, {"date": {"year": 2019, "month": 11}, "value": 105.18390865662195}, {"date": {"year": 2019, "month": 12}, "value": 106.71191641697614}, {"date": {"year": 2020, "month": 1}, "value": 107.4387176445696}, {"date": {"year": 2020, "month": 2}, "value": 107.80265238487274}, {"date": {"year": 2020, "month": 3}, "value": 108.13822447046017}, {"date": {"year": 2020, "month": 4}, "value": 108.18670945697342}, {"date": {"year": 2020, "month": 5}, "value": 107.93319682310603}, {"date": {"year": 2020, "month": 6}, "value": 107.70449184424926}, {"date": {"year": 2020, "month": 7}, "value": 109.38119969529426}, {"date": {"year": 2020, "month": 8}, "value": 109.7391716074245}, {"date": {"year": 2020, "month": 9}, "value": 110.45104616923606}, {"date": {"year": 2020, "month": 10}, "value": 110.69062446907304}, {"date": {"year": 2020, "month": 11}, "value": 111.67281638070192}, {"date": {"year": 2020, "month": 12}, "value": 112.52840379763575}, {"date": {"year": 2021, "month": 1}, "value": 113.63004263483403}, {"date": {"year": 2021, "month": 2}, "value": 115.24328515166327}, {"date": {"year": 2021, "month": 3}, "value": 115.99692420203485}, {"date": {"year": 2021, "month": 4}, "value": 116.92176216268018}, {"date": {"year": 2021, "month": 5}, "value": 116.8689067472732}, {"date": {"year": 2021, "month": 6}, "value": 118.22511247207763}, {"date": {"year": 2021, "month": 7}, "value": 118.59403074558817}, {"date": {"year": 2021, "month": 8}, "value": 119.2673733794348}, {"date": {"year": 2021, "month": 9}, "value": 119.53324541803991}, {"date": {"year": 2021, "month": 10}, "value": 120.10806198003178}, {"date": {"year": 2021, "month": 11}, "value": 121.21468349928557}, {"date": {"year": 2021, "month": 12}, "value": 122.9330896113028}, {"date": {"year": 2022, "month": 1}, "value": 124.62347099056433}, {"date": {"year": 2022, "month": 2}, "value": 124.970202173508}, {"date": {"year": 2022, "month": 3}, "value": 125.46013170260215}, {"date": {"year": 2022, "month": 4}, "value": 127.47336096601435}], "by": "by-region"}, {"name": "Alimentos e Bebidas n\u00e3o Alco\u00f3licas", "by": "by-product", "values": [{"date": {"year": 2018, "month": 1}, "value": 100.0}, {"date": {"year": 2018, "month": 2}, "value": 99.18034281975223}, {"date": {"year": 2018, "month": 3}, "value": 99.41828230517052}, {"date": {"year": 2018, "month": 4}, "value": 100.43071496917533}, {"date": {"year": 2018, "month": 5}, "value": 100.61497864638109}, {"date": {"year": 2018, "month": 6}, "value": 100.14561621427578}, {"date": {"year": 2018, "month": 7}, "value": 99.78712599662293}, {"date": {"year": 2018, "month": 8}, "value": 99.7729056424961}, {"date": {"year": 2018, "month": 9}, "value": 99.82654626857358}, {"date": {"year": 2018, "month": 10}, "value": 100.12565652883339}, {"date": {"year": 2018, "month": 11}, "value": 100.61073792237707}, {"date": {"year": 2018, "month": 12}, "value": 101.12947086690711}, {"date": {"year": 2019, "month": 1}, "value": 101.45126267170204}, {"date": {"year": 2019, "month": 2}, "value": 102.33077794296945}, {"date": {"year": 2019, "month": 3}, "value": 102.18027049453478}, {"date": {"year": 2019, "month": 4}, "value": 102.20690108096224}, {"date": {"year": 2019, "month": 5}, "value": 100.52099249701376}, {"date": {"year": 2019, "month": 6}, "value": 100.08812534652603}, {"date": {"year": 2019, "month": 7}, "value": 100.94872685927592}, {"date": {"year": 2019, "month": 8}, "value": 101.85301997058038}, {"date": {"year": 2019, "month": 9}, "value": 103.70235804896357}, {"date": {"year": 2019, "month": 10}, "value": 104.97798516014231}, {"date": {"year": 2019, "month": 11}, "value": 105.064914510059}, {"date": {"year": 2019, "month": 12}, "value": 108.63399414597785}, {"date": {"year": 2020, "month": 1}, "value": 110.17504532468098}, {"date": {"year": 2020, "month": 2}, "value": 110.40364949238794}, {"date": {"year": 2020, "month": 3}, "value": 111.21137650722805}, {"date": {"year": 2020, "month": 4}, "value": 110.9555287991584}, {"date": {"year": 2020, "month": 5}, "value": 110.80414758104578}, {"date": {"year": 2020, "month": 6}, "value": 109.28547107748896}, {"date": {"year": 2020, "month": 7}, "value": 110.75542926803608}, {"date": {"year": 2020, "month": 8}, "value": 111.62390595431009}, {"date": {"year": 2020, "month": 9}, "value": 112.35993526762422}, {"date": {"year": 2020, "month": 10}, "value": 112.67675115174669}, {"date": {"year": 2020, "month": 11}, "value": 113.86547330501725}, {"date": {"year": 2020, "month": 12}, "value": 116.22594194820908}, {"date": {"year": 2021, "month": 1}, "value": 119.16589843419818}, {"date": {"year": 2021, "month": 2}, "value": 121.25659271901775}, {"date": {"year": 2021, "month": 3}, "value": 122.23164829818975}, {"date": {"year": 2021, "month": 4}, "value": 122.711706489115}, {"date": {"year": 2021, "month": 5}, "value": 121.52245757946409}, {"date": {"year": 2021, "month": 6}, "value": 125.17110858313467}, {"date": {"year": 2021, "month": 7}, "value": 126.06202256618475}, {"date": {"year": 2021, "month": 8}, "value": 125.87186421523293}, {"date": {"year": 2021, "month": 9}, "value": 126.11689485164757}, {"date": {"year": 2021, "month": 10}, "value": 126.278643795474}, {"date": {"year": 2021, "month": 11}, "value": 126.50578777023134}, {"date": {"year": 2021, "month": 12}, "value": 129.04398101311727}, {"date": {"year": 2022, "month": 1}, "value": 130.58396958266732}, {"date": {"year": 2022, "month": 2}, "value": 131.4653449368391}, {"date": {"year": 2022, "month": 3}, "value": 132.2159894206807}, {"date": {"year": 2022, "month": 4}, "value": 130.20917548544412}]}, {"name": "Bebidas Alco\u00f3licas, Tabaco e Narc\u00f3ticos", "by": "by-product", "values": [{"date": {"year": 2018, "month": 1}, "value": 100.0}, {"date": {"year": 2018, "month": 2}, "value": 99.14497554104439}, {"date": {"year": 2018, "month": 3}, "value": 98.0118564369348}, {"date": {"year": 2018, "month": 4}, "value": 98.0118564369348}, {"date": {"year": 2018, "month": 5}, "value": 98.0118564369348}, {"date": {"year": 2018, "month": 6}, "value": 99.02824492514645}, {"date": {"year": 2018, "month": 7}, "value": 100.52100115260956}, {"date": {"year": 2018, "month": 8}, "value": 100.56469309075497}, {"date": {"year": 2018, "month": 9}, "value": 100.96606265204413}, {"date": {"year": 2018, "month": 10}, "value": 100.96606265204413}, {"date": {"year": 2018, "month": 11}, "value": 102.89782622585568}, {"date": {"year": 2018, "month": 12}, "value": 102.89782622585568}, {"date": {"year": 2019, "month": 1}, "value": 102.89782622585568}, {"date": {"year": 2019, "month": 2}, "value": 102.89782622585568}, {"date": {"year": 2019, "month": 3}, "value": 102.89782622585568}, {"date": {"year": 2019, "month": 4}, "value": 102.89782622585568}, {"date": {"year": 2019, "month": 5}, "value": 120.2253206664362}, {"date": {"year": 2019, "month": 6}, "value": 120.36906252644492}, {"date": {"year": 2019, "month": 7}, "value": 126.70587084050358}, {"date": {"year": 2019, "month": 8}, "value": 135.79887899114323}, {"date": {"year": 2019, "month": 9}, "value": 142.30461638247849}, {"date": {"year": 2019, "month": 10}, "value": 142.30461638247849}, {"date": {"year": 2019, "month": 11}, "value": 142.4000304248101}, {"date": {"year": 2019, "month": 12}, "value": 142.58685861007532}, {"date": {"year": 2020, "month": 1}, "value": 143.92313131767534}, {"date": {"year": 2020, "month": 2}, "value": 145.52664561758175}, {"date": {"year": 2020, "month": 3}, "value": 143.62192673380355}, {"date": {"year": 2020, "month": 4}, "value": 143.62192673380355}, {"date": {"year": 2020, "month": 5}, "value": 144.28383155720954}, {"date": {"year": 2020, "month": 6}, "value": 147.30573930720578}, {"date": {"year": 2020, "month": 7}, "value": 145.9379340313265}, {"date": {"year": 2020, "month": 8}, "value": 146.08327750872562}, {"date": {"year": 2020, "month": 9}, "value": 145.1592425453609}, {"date": {"year": 2020, "month": 10}, "value": 144.35643633144798}, {"date": {"year": 2020, "month": 11}, "value": 149.53237492313133}, {"date": {"year": 2020, "month": 12}, "value": 149.4530294446824}, {"date": {"year": 2021, "month": 1}, "value": 148.81228216623944}, {"date": {"year": 2021, "month": 2}, "value": 148.61912979119745}, {"date": {"year": 2021, "month": 3}, "value": 150.50759449541638}, {"date": {"year": 2021, "month": 4}, "value": 154.61106754215376}, {"date": {"year": 2021, "month": 5}, "value": 159.0754889999461}, {"date": {"year": 2021, "month": 6}, "value": 159.6087957836629}, {"date": {"year": 2021, "month": 7}, "value": 159.62474001409072}, {"date": {"year": 2021, "month": 8}, "value": 157.22936253315544}, {"date": {"year": 2021, "month": 9}, "value": 159.2461095675121}, {"date": {"year": 2021, "month": 10}, "value": 163.62189561410437}, {"date": {"year": 2021, "month": 11}, "value": 174.47926184363172}, {"date": {"year": 2021, "month": 12}, "value": 174.51115030448724}, {"date": {"year": 2022, "month": 1}, "value": 174.6852971160161}, {"date": {"year": 2022, "month": 2}, "value": 174.710867835243}, {"date": {"year": 2022, "month": 3}, "value": 174.73142607575204}, {"date": {"year": 2022, "month": 4}, "value": 174.3318037873152}]}, {"name": "Vestu\u00e1rios e Cal\u00e7ados", "by": "by-product", "values": [{"date": {"year": 2018, "month": 1}, "value": 100.0}, {"date": {"year": 2018, "month": 2}, "value": 99.9434827165589}, {"date": {"year": 2018, "month": 3}, "value": 99.97425551798402}, {"date": {"year": 2018, "month": 4}, "value": 101.8234440290058}, {"date": {"year": 2018, "month": 5}, "value": 102.91288409153563}, {"date": {"year": 2018, "month": 6}, "value": 98.59552468157624}, {"date": {"year": 2018, "month": 7}, "value": 98.59249404719147}, {"date": {"year": 2018, "month": 8}, "value": 98.83591612297185}, {"date": {"year": 2018, "month": 9}, "value": 99.63672633408743}, {"date": {"year": 2018, "month": 10}, "value": 99.41689491514421}, {"date": {"year": 2018, "month": 11}, "value": 100.1462459139429}, {"date": {"year": 2018, "month": 12}, "value": 100.1478761120175}, {"date": {"year": 2019, "month": 1}, "value": 100.51541916306248}, {"date": {"year": 2019, "month": 2}, "value": 100.50908649872827}, {"date": {"year": 2019, "month": 3}, "value": 100.76066765953485}, {"date": {"year": 2019, "month": 4}, "value": 99.4331486604385}, {"date": {"year": 2019, "month": 5}, "value": 92.9601377241946}, {"date": {"year": 2019, "month": 6}, "value": 93.18930749821317}, {"date": {"year": 2019, "month": 7}, "value": 96.75181605846758}, {"date": {"year": 2019, "month": 8}, "value": 105.34124539778045}, {"date": {"year": 2019, "month": 9}, "value": 108.44189876365455}, {"date": {"year": 2019, "month": 10}, "value": 108.7311825707683}, {"date": {"year": 2019, "month": 11}, "value": 108.65794968898896}, {"date": {"year": 2019, "month": 12}, "value": 108.17931738773274}, {"date": {"year": 2020, "month": 1}, "value": 108.19033933939674}, {"date": {"year": 2020, "month": 2}, "value": 109.54500312047237}, {"date": {"year": 2020, "month": 3}, "value": 109.56940513544404}, {"date": {"year": 2020, "month": 4}, "value": 110.38878681475295}, {"date": {"year": 2020, "month": 5}, "value": 109.16092255486075}, {"date": {"year": 2020, "month": 6}, "value": 108.50854939409247}, {"date": {"year": 2020, "month": 7}, "value": 110.46892642616717}, {"date": {"year": 2020, "month": 8}, "value": 110.03678795561365}, {"date": {"year": 2020, "month": 9}, "value": 112.70377590674316}, {"date": {"year": 2020, "month": 10}, "value": 113.05055688023575}, {"date": {"year": 2020, "month": 11}, "value": 115.5021761713962}, {"date": {"year": 2020, "month": 12}, "value": 115.1839797497219}, {"date": {"year": 2021, "month": 1}, "value": 113.83160492871365}, {"date": {"year": 2021, "month": 2}, "value": 113.85776595109192}, {"date": {"year": 2021, "month": 3}, "value": 113.66937665545235}, {"date": {"year": 2021, "month": 4}, "value": 113.65475660162305}, {"date": {"year": 2021, "month": 5}, "value": 113.96055412790203}, {"date": {"year": 2021, "month": 6}, "value": 114.13954465344493}, {"date": {"year": 2021, "month": 7}, "value": 113.8326998841773}, {"date": {"year": 2021, "month": 8}, "value": 113.8326998841773}, {"date": {"year": 2021, "month": 9}, "value": 113.35141237201624}, {"date": {"year": 2021, "month": 10}, "value": 114.28609524385054}, {"date": {"year": 2021, "month": 11}, "value": 114.88328558717997}, {"date": {"year": 2021, "month": 12}, "value": 114.75801610646982}, {"date": {"year": 2022, "month": 1}, "value": 114.94537429024842}, {"date": {"year": 2022, "month": 2}, "value": 114.6917805173538}, {"date": {"year": 2022, "month": 3}, "value": 113.21601226464833}, {"date": {"year": 2022, "month": 4}, "value": 115.68374604375838}]}, {"name": "Habita\u00e7\u00e3o, \u00c1gua, Electricidade, G\u00e1s e Outros Combust\u00edveis", "by": "by-product", "values": [{"date": {"year": 2018, "month": 1}, "value": 100.0}, {"date": {"year": 2018, "month": 2}, "value": 99.21506040972872}, {"date": {"year": 2018, "month": 3}, "value": 99.22962519435572}, {"date": {"year": 2018, "month": 4}, "value": 99.56082253927161}, {"date": {"year": 2018, "month": 5}, "value": 99.95007114136307}, {"date": {"year": 2018, "month": 6}, "value": 100.14596284324475}, {"date": {"year": 2018, "month": 7}, "value": 99.95447730580656}, {"date": {"year": 2018, "month": 8}, "value": 99.95447730580656}, {"date": {"year": 2018, "month": 9}, "value": 100.51443550184405}, {"date": {"year": 2018, "month": 10}, "value": 100.57293336190858}, {"date": {"year": 2018, "month": 11}, "value": 100.6011506382045}, {"date": {"year": 2018, "month": 12}, "value": 101.10349785709376}, {"date": {"year": 2019, "month": 1}, "value": 101.71344962047964}, {"date": {"year": 2019, "month": 2}, "value": 102.53565994293005}, {"date": {"year": 2019, "month": 3}, "value": 102.52169017917872}, {"date": {"year": 2019, "month": 4}, "value": 102.45791678382885}, {"date": {"year": 2019, "month": 5}, "value": 102.52518981179198}, {"date": {"year": 2019, "month": 6}, "value": 102.61124972528182}, {"date": {"year": 2019, "month": 7}, "value": 102.86444312863574}, {"date": {"year": 2019, "month": 8}, "value": 95.43431925787483}, {"date": {"year": 2019, "month": 9}, "value": 96.3828833872291}, {"date": {"year": 2019, "month": 10}, "value": 98.20846116941875}, {"date": {"year": 2019, "month": 11}, "value": 98.28545235288458}, {"date": {"year": 2019, "month": 12}, "value": 98.28545235288458}, {"date": {"year": 2020, "month": 1}, "value": 98.49900262454871}, {"date": {"year": 2020, "month": 2}, "value": 98.49900262454871}, {"date": {"year": 2020, "month": 3}, "value": 98.6057777603808}, {"date": {"year": 2020, "month": 4}, "value": 98.62357361635281}, {"date": {"year": 2020, "month": 5}, "value": 98.49900262454871}, {"date": {"year": 2020, "month": 6}, "value": 98.48668810531548}, {"date": {"year": 2020, "month": 7}, "value": 98.46890498066738}, {"date": {"year": 2020, "month": 8}, "value": 98.46890498066738}, {"date": {"year": 2020, "month": 9}, "value": 100.79609380899453}, {"date": {"year": 2020, "month": 10}, "value": 100.79609380899453}, {"date": {"year": 2020, "month": 11}, "value": 99.81737220206377}, {"date": {"year": 2020, "month": 12}, "value": 99.81737220206377}, {"date": {"year": 2021, "month": 1}, "value": 99.91987633246254}, {"date": {"year": 2021, "month": 2}, "value": 99.81737220206377}, {"date": {"year": 2021, "month": 3}, "value": 99.90279231072941}, {"date": {"year": 2021, "month": 4}, "value": 99.98821241939507}, {"date": {"year": 2021, "month": 5}, "value": 103.03869339785321}, {"date": {"year": 2021, "month": 6}, "value": 103.03869339785321}, {"date": {"year": 2021, "month": 7}, "value": 101.91358710185352}, {"date": {"year": 2021, "month": 8}, "value": 98.5382682138545}, {"date": {"year": 2021, "month": 9}, "value": 98.5382682138545}, {"date": {"year": 2021, "month": 10}, "value": 98.53928703870413}, {"date": {"year": 2021, "month": 11}, "value": 102.00513387842629}, {"date": {"year": 2021, "month": 12}, "value": 104.25534647042562}, {"date": {"year": 2022, "month": 1}, "value": 108.75577165442434}, {"date": {"year": 2022, "month": 2}, "value": 108.75577165442434}, {"date": {"year": 2022, "month": 3}, "value": 108.75577165442434}, {"date": {"year": 2022, "month": 4}, "value": 108.21368762385801}]}, {"name": "Mobili\u00e1rio, Artigos de Decora\u00e7\u00e3o, Equipamento Dom\u00e9stico e Manuten\u00e7\u00e3o da Habita\u00e7\u00e3o", "by": "by-product", "values": [{"date": {"year": 2018, "month": 1}, "value": 100.0}, {"date": {"year": 2018, "month": 2}, "value": 99.61638333873968}, {"date": {"year": 2018, "month": 3}, "value": 99.70337441337962}, {"date": {"year": 2018, "month": 4}, "value": 99.67804884720069}, {"date": {"year": 2018, "month": 5}, "value": 99.69860253163911}, {"date": {"year": 2018, "month": 6}, "value": 99.80589186996411}, {"date": {"year": 2018, "month": 7}, "value": 99.86323906659743}, {"date": {"year": 2018, "month": 8}, "value": 100.51514841889902}, {"date": {"year": 2018, "month": 9}, "value": 100.11415260855105}, {"date": {"year": 2018, "month": 10}, "value": 100.56775499615871}, {"date": {"year": 2018, "month": 11}, "value": 100.38770613827653}, {"date": {"year": 2018, "month": 12}, "value": 100.4162517568012}, {"date": {"year": 2019, "month": 1}, "value": 100.44102728343292}, {"date": {"year": 2019, "month": 2}, "value": 100.61329789193107}, {"date": {"year": 2019, "month": 3}, "value": 100.67935399335262}, {"date": {"year": 2019, "month": 4}, "value": 100.51103700989714}, {"date": {"year": 2019, "month": 5}, "value": 97.83731966043835}, {"date": {"year": 2019, "month": 6}, "value": 97.99345847783158}, {"date": {"year": 2019, "month": 7}, "value": 97.14196089325024}, {"date": {"year": 2019, "month": 8}, "value": 95.1909221164297}, {"date": {"year": 2019, "month": 9}, "value": 97.49572974063523}, {"date": {"year": 2019, "month": 10}, "value": 97.85078400635277}, {"date": {"year": 2019, "month": 11}, "value": 96.61606000288748}, {"date": {"year": 2019, "month": 12}, "value": 96.89523289482234}, {"date": {"year": 2020, "month": 1}, "value": 97.06153540575465}, {"date": {"year": 2020, "month": 2}, "value": 97.58966042501473}, {"date": {"year": 2020, "month": 3}, "value": 98.05006191458898}, {"date": {"year": 2020, "month": 4}, "value": 98.0654614066418}, {"date": {"year": 2020, "month": 5}, "value": 99.3091163573394}, {"date": {"year": 2020, "month": 6}, "value": 101.81259060202646}, {"date": {"year": 2020, "month": 7}, "value": 102.2682180061448}, {"date": {"year": 2020, "month": 8}, "value": 101.16442996787312}, {"date": {"year": 2020, "month": 9}, "value": 100.29135788490578}, {"date": {"year": 2020, "month": 10}, "value": 101.04244060776921}, {"date": {"year": 2020, "month": 11}, "value": 99.646496376375}, {"date": {"year": 2020, "month": 12}, "value": 99.662913821311}, {"date": {"year": 2021, "month": 1}, "value": 99.69196107597863}, {"date": {"year": 2021, "month": 2}, "value": 100.0755383584111}, {"date": {"year": 2021, "month": 3}, "value": 100.76543950558663}, {"date": {"year": 2021, "month": 4}, "value": 101.17382960611998}, {"date": {"year": 2021, "month": 5}, "value": 105.36993859239516}, {"date": {"year": 2021, "month": 6}, "value": 108.1919751585929}, {"date": {"year": 2021, "month": 7}, "value": 108.4803607237707}, {"date": {"year": 2021, "month": 8}, "value": 106.65851975537875}, {"date": {"year": 2021, "month": 9}, "value": 106.64275999899418}, {"date": {"year": 2021, "month": 10}, "value": 106.93772361225768}, {"date": {"year": 2021, "month": 11}, "value": 107.78126234555845}, {"date": {"year": 2021, "month": 12}, "value": 109.43694254095651}, {"date": {"year": 2022, "month": 1}, "value": 109.50074680307848}, {"date": {"year": 2022, "month": 2}, "value": 110.17219772240439}, {"date": {"year": 2022, "month": 3}, "value": 111.71503488199197}, {"date": {"year": 2022, "month": 4}, "value": 112.60058367733909}]}, {"name": "Sa\u00fade", "by": "by-product", "values": [{"date": {"year": 2018, "month": 1}, "value": 100.0}, {"date": {"year": 2018, "month": 2}, "value": 100.43186434148723}, {"date": {"year": 2018, "month": 3}, "value": 100.02697409063539}, {"date": {"year": 2018, "month": 4}, "value": 99.95416588215242}, {"date": {"year": 2018, "month": 5}, "value": 99.95416588215242}, {"date": {"year": 2018, "month": 6}, "value": 99.95893274652269}, {"date": {"year": 2018, "month": 7}, "value": 99.81331632955676}, {"date": {"year": 2018, "month": 8}, "value": 99.73454954061094}, {"date": {"year": 2018, "month": 9}, "value": 99.48041363615087}, {"date": {"year": 2018, "month": 10}, "value": 99.662285575916}, {"date": {"year": 2018, "month": 11}, "value": 100.27394624252517}, {"date": {"year": 2018, "month": 12}, "value": 100.27394624252517}, {"date": {"year": 2019, "month": 1}, "value": 100.26798766206232}, {"date": {"year": 2019, "month": 2}, "value": 100.4432264796525}, {"date": {"year": 2019, "month": 3}, "value": 100.65155926116962}, {"date": {"year": 2019, "month": 4}, "value": 100.66674030670526}, {"date": {"year": 2019, "month": 5}, "value": 100.66674030670526}, {"date": {"year": 2019, "month": 6}, "value": 100.66674030670526}, {"date": {"year": 2019, "month": 7}, "value": 99.81598917212536}, {"date": {"year": 2019, "month": 8}, "value": 99.89374551885257}, {"date": {"year": 2019, "month": 9}, "value": 97.60039032982563}, {"date": {"year": 2019, "month": 10}, "value": 97.59345828953617}, {"date": {"year": 2019, "month": 11}, "value": 97.14520278281195}, {"date": {"year": 2019, "month": 12}, "value": 97.24188873077047}, {"date": {"year": 2020, "month": 1}, "value": 97.38739410113872}, {"date": {"year": 2020, "month": 2}, "value": 98.3185979858931}, {"date": {"year": 2020, "month": 3}, "value": 98.79430848209402}, {"date": {"year": 2020, "month": 4}, "value": 98.79430848209402}, {"date": {"year": 2020, "month": 5}, "value": 99.62831215511162}, {"date": {"year": 2020, "month": 6}, "value": 98.17197397634635}, {"date": {"year": 2020, "month": 7}, "value": 97.31545270251249}, {"date": {"year": 2020, "month": 8}, "value": 99.33834485327704}, {"date": {"year": 2020, "month": 9}, "value": 99.64728248820711}, {"date": {"year": 2020, "month": 10}, "value": 96.66085823198421}, {"date": {"year": 2020, "month": 11}, "value": 96.6591580718948}, {"date": {"year": 2020, "month": 12}, "value": 96.54136371102993}, {"date": {"year": 2021, "month": 1}, "value": 96.97017648542695}, {"date": {"year": 2021, "month": 2}, "value": 96.87922190365336}, {"date": {"year": 2021, "month": 3}, "value": 94.69341678018041}, {"date": {"year": 2021, "month": 4}, "value": 94.61139485694135}, {"date": {"year": 2021, "month": 5}, "value": 94.2300079702393}, {"date": {"year": 2021, "month": 6}, "value": 94.23403385717639}, {"date": {"year": 2021, "month": 7}, "value": 95.64286309926102}, {"date": {"year": 2021, "month": 8}, "value": 94.46082656575004}, {"date": {"year": 2021, "month": 9}, "value": 94.36452159630181}, {"date": {"year": 2021, "month": 10}, "value": 94.30668287403326}, {"date": {"year": 2021, "month": 11}, "value": 94.9256116586852}, {"date": {"year": 2021, "month": 12}, "value": 94.79806107852279}, {"date": {"year": 2022, "month": 1}, "value": 95.51276262125371}, {"date": {"year": 2022, "month": 2}, "value": 95.0418325984543}, {"date": {"year": 2022, "month": 3}, "value": 94.4734582434501}, {"date": {"year": 2022, "month": 4}, "value": 94.37211218542478}]}, {"name": "Transportes", "by": "by-product", "values": [{"date": {"year": 2018, "month": 1}, "value": 100.0}, {"date": {"year": 2018, "month": 2}, "value": 98.7670848701699}, {"date": {"year": 2018, "month": 3}, "value": 99.77163476626677}, {"date": {"year": 2018, "month": 4}, "value": 99.77163476626677}, {"date": {"year": 2018, "month": 5}, "value": 99.77163476626677}, {"date": {"year": 2018, "month": 6}, "value": 99.77163476626677}, {"date": {"year": 2018, "month": 7}, "value": 100.14542077411679}, {"date": {"year": 2018, "month": 8}, "value": 100.51495921369576}, {"date": {"year": 2018, "month": 9}, "value": 100.51495921369576}, {"date": {"year": 2018, "month": 10}, "value": 100.51495921369576}, {"date": {"year": 2018, "month": 11}, "value": 100.84449638969453}, {"date": {"year": 2018, "month": 12}, "value": 100.84449638969453}, {"date": {"year": 2019, "month": 1}, "value": 100.84449638969453}, {"date": {"year": 2019, "month": 2}, "value": 101.297965135931}, {"date": {"year": 2019, "month": 3}, "value": 101.297965135931}, {"date": {"year": 2019, "month": 4}, "value": 101.08346293824432}, {"date": {"year": 2019, "month": 5}, "value": 101.08346293824432}, {"date": {"year": 2019, "month": 6}, "value": 101.08334204180245}, {"date": {"year": 2019, "month": 7}, "value": 101.95239593443648}, {"date": {"year": 2019, "month": 8}, "value": 101.81824302316198}, {"date": {"year": 2019, "month": 9}, "value": 101.84242231153596}, {"date": {"year": 2019, "month": 10}, "value": 101.89097288178577}, {"date": {"year": 2019, "month": 11}, "value": 101.89097288178577}, {"date": {"year": 2019, "month": 12}, "value": 101.89097288178577}, {"date": {"year": 2020, "month": 1}, "value": 101.89097288178577}, {"date": {"year": 2020, "month": 2}, "value": 101.6012882509078}, {"date": {"year": 2020, "month": 3}, "value": 101.6012882509078}, {"date": {"year": 2020, "month": 4}, "value": 101.6012882509078}, {"date": {"year": 2020, "month": 5}, "value": 100.86828518849372}, {"date": {"year": 2020, "month": 6}, "value": 100.22051564940966}, {"date": {"year": 2020, "month": 7}, "value": 100.07389955608855}, {"date": {"year": 2020, "month": 8}, "value": 100.08217373614482}, {"date": {"year": 2020, "month": 9}, "value": 100.06533343900237}, {"date": {"year": 2020, "month": 10}, "value": 100.06533343900237}, {"date": {"year": 2020, "month": 11}, "value": 102.3330711907241}, {"date": {"year": 2020, "month": 12}, "value": 102.02177327533717}, {"date": {"year": 2021, "month": 1}, "value": 102.02177327533717}, {"date": {"year": 2021, "month": 2}, "value": 104.91861958411715}, {"date": {"year": 2021, "month": 3}, "value": 104.94988650670822}, {"date": {"year": 2021, "month": 4}, "value": 104.59364623594793}, {"date": {"year": 2021, "month": 5}, "value": 104.59364623594793}, {"date": {"year": 2021, "month": 6}, "value": 103.79478060570906}, {"date": {"year": 2021, "month": 7}, "value": 103.79478060570906}, {"date": {"year": 2021, "month": 8}, "value": 103.79478060570906}, {"date": {"year": 2021, "month": 9}, "value": 103.79478060570906}, {"date": {"year": 2021, "month": 10}, "value": 104.54023250876124}, {"date": {"year": 2021, "month": 11}, "value": 105.92911742351451}, {"date": {"year": 2021, "month": 12}, "value": 105.92911742351451}, {"date": {"year": 2022, "month": 1}, "value": 105.92911742351451}, {"date": {"year": 2022, "month": 2}, "value": 106.38258616975097}, {"date": {"year": 2022, "month": 3}, "value": 110.02200760578258}, {"date": {"year": 2022, "month": 4}, "value": 128.2386061139363}]}, {"name": "Comunica\u00e7\u00f5es", "by": "by-product", "values": [{"date": {"year": 2018, "month": 1}, "value": 100.0}, {"date": {"year": 2018, "month": 2}, "value": 98.4495602056547}, {"date": {"year": 2018, "month": 3}, "value": 98.4495602056547}, {"date": {"year": 2018, "month": 4}, "value": 98.4495602056547}, {"date": {"year": 2018, "month": 5}, "value": 98.4495602056547}, {"date": {"year": 2018, "month": 6}, "value": 98.4495602056547}, {"date": {"year": 2018, "month": 7}, "value": 101.55043979434531}, {"date": {"year": 2018, "month": 8}, "value": 101.55043979434531}, {"date": {"year": 2018, "month": 9}, "value": 101.55043979434531}, {"date": {"year": 2018, "month": 10}, "value": 101.55043979434531}, {"date": {"year": 2018, "month": 11}, "value": 101.55043979434531}, {"date": {"year": 2018, "month": 12}, "value": 101.55043979434531}, {"date": {"year": 2019, "month": 1}, "value": 101.55043979434531}, {"date": {"year": 2019, "month": 2}, "value": 101.55043979434531}, {"date": {"year": 2019, "month": 3}, "value": 101.55043979434531}, {"date": {"year": 2019, "month": 4}, "value": 101.55043979434531}, {"date": {"year": 2019, "month": 5}, "value": 101.71446790888423}, {"date": {"year": 2019, "month": 6}, "value": 101.13989732786335}, {"date": {"year": 2019, "month": 7}, "value": 101.04413556435988}, {"date": {"year": 2019, "month": 8}, "value": 102.48056201691209}, {"date": {"year": 2019, "month": 9}, "value": 101.99537466152826}, {"date": {"year": 2019, "month": 10}, "value": 101.99537466152826}, {"date": {"year": 2019, "month": 11}, "value": 101.84678865108192}, {"date": {"year": 2019, "month": 12}, "value": 101.84678865108192}, {"date": {"year": 2020, "month": 1}, "value": 101.84678865108192}, {"date": {"year": 2020, "month": 2}, "value": 101.62390963541239}, {"date": {"year": 2020, "month": 3}, "value": 101.54961663018922}, {"date": {"year": 2020, "month": 4}, "value": 101.54961663018922}, {"date": {"year": 2020, "month": 5}, "value": 101.84678865108192}, {"date": {"year": 2020, "month": 6}, "value": 101.99537466152826}, {"date": {"year": 2020, "month": 7}, "value": 102.29254668242096}, {"date": {"year": 2020, "month": 8}, "value": 102.29254668242096}, {"date": {"year": 2020, "month": 9}, "value": 102.2182536771978}, {"date": {"year": 2020, "month": 10}, "value": 102.29254668242096}, {"date": {"year": 2020, "month": 11}, "value": 101.77249564585875}, {"date": {"year": 2020, "month": 12}, "value": 100.13804953094889}, {"date": {"year": 2021, "month": 1}, "value": 100.13804953094889}, {"date": {"year": 2021, "month": 2}, "value": 100.13804953094889}, {"date": {"year": 2021, "month": 3}, "value": 100.47236805445318}, {"date": {"year": 2021, "month": 4}, "value": 101.06671209623859}, {"date": {"year": 2021, "month": 5}, "value": 100.99241909101542}, {"date": {"year": 2021, "month": 6}, "value": 100.99241909101542}, {"date": {"year": 2021, "month": 7}, "value": 100.99241909101542}, {"date": {"year": 2021, "month": 8}, "value": 100.99241909101542}, {"date": {"year": 2021, "month": 9}, "value": 100.99241909101542}, {"date": {"year": 2021, "month": 10}, "value": 100.99241909101542}, {"date": {"year": 2021, "month": 11}, "value": 100.99241909101542}, {"date": {"year": 2021, "month": 12}, "value": 100.99241909101542}, {"date": {"year": 2022, "month": 1}, "value": 100.99241909101542}, {"date": {"year": 2022, "month": 2}, "value": 101.14100510146176}, {"date": {"year": 2022, "month": 3}, "value": 101.21529810668494}, {"date": {"year": 2022, "month": 4}, "value": 101.21529810668494}]}, {"name": "Lazer, Recrea\u00e7\u00e3o e Cultura", "by": "by-product", "values": [{"date": {"year": 2018, "month": 1}, "value": 100.0}, {"date": {"year": 2018, "month": 2}, "value": 94.94009460503634}, {"date": {"year": 2018, "month": 3}, "value": 97.10406403834817}, {"date": {"year": 2018, "month": 4}, "value": 97.10406403834817}, {"date": {"year": 2018, "month": 5}, "value": 98.35135580228054}, {"date": {"year": 2018, "month": 6}, "value": 98.37382927199837}, {"date": {"year": 2018, "month": 7}, "value": 101.75198015640825}, {"date": {"year": 2018, "month": 8}, "value": 101.75198015640825}, {"date": {"year": 2018, "month": 9}, "value": 102.93232712003058}, {"date": {"year": 2018, "month": 10}, "value": 102.93232712003058}, {"date": {"year": 2018, "month": 11}, "value": 103.82695682638132}, {"date": {"year": 2018, "month": 12}, "value": 103.82695682638132}, {"date": {"year": 2019, "month": 1}, "value": 103.82695682638132}, {"date": {"year": 2019, "month": 2}, "value": 103.80448335666348}, {"date": {"year": 2019, "month": 3}, "value": 103.80448335666348}, {"date": {"year": 2019, "month": 4}, "value": 103.80448335666348}, {"date": {"year": 2019, "month": 5}, "value": 105.72038861122823}, {"date": {"year": 2019, "month": 6}, "value": 105.78050965750425}, {"date": {"year": 2019, "month": 7}, "value": 105.78422791074304}, {"date": {"year": 2019, "month": 8}, "value": 110.57127820546509}, {"date": {"year": 2019, "month": 9}, "value": 110.63671600339875}, {"date": {"year": 2019, "month": 10}, "value": 111.3109200949337}, {"date": {"year": 2019, "month": 11}, "value": 111.1456355905482}, {"date": {"year": 2019, "month": 12}, "value": 110.80315050512772}, {"date": {"year": 2020, "month": 1}, "value": 110.9133924854133}, {"date": {"year": 2020, "month": 2}, "value": 110.55829015492237}, {"date": {"year": 2020, "month": 3}, "value": 110.57298908562711}, {"date": {"year": 2020, "month": 4}, "value": 110.57298908562711}, {"date": {"year": 2020, "month": 5}, "value": 110.46274710534156}, {"date": {"year": 2020, "month": 6}, "value": 107.23204247532259}, {"date": {"year": 2020, "month": 7}, "value": 104.00084801042154}, {"date": {"year": 2020, "month": 8}, "value": 111.11739264059948}, {"date": {"year": 2020, "month": 9}, "value": 111.29820022431385}, {"date": {"year": 2020, "month": 10}, "value": 115.15835871735902}, {"date": {"year": 2020, "month": 11}, "value": 108.24850638697778}, {"date": {"year": 2020, "month": 12}, "value": 108.1382644066922}, {"date": {"year": 2021, "month": 1}, "value": 108.1382644066922}, {"date": {"year": 2021, "month": 2}, "value": 107.02381012628146}, {"date": {"year": 2021, "month": 3}, "value": 106.91525732904658}, {"date": {"year": 2021, "month": 4}, "value": 106.91975202299015}, {"date": {"year": 2021, "month": 5}, "value": 107.54445657794163}, {"date": {"year": 2021, "month": 6}, "value": 108.94085499489204}, {"date": {"year": 2021, "month": 7}, "value": 106.956499349752}, {"date": {"year": 2021, "month": 8}, "value": 106.10028663620086}, {"date": {"year": 2021, "month": 9}, "value": 106.10028663620086}, {"date": {"year": 2021, "month": 10}, "value": 106.21052861648639}, {"date": {"year": 2021, "month": 11}, "value": 106.21052861648639}, {"date": {"year": 2021, "month": 12}, "value": 106.85043599629718}, {"date": {"year": 2022, "month": 1}, "value": 106.85043599629718}, {"date": {"year": 2022, "month": 2}, "value": 106.85043599629718}, {"date": {"year": 2022, "month": 3}, "value": 106.70375258553166}, {"date": {"year": 2022, "month": 4}, "value": 109.00006175780801}]}, {"name": "Educa\u00e7\u00e3o", "by": "by-product", "values": [{"date": {"year": 2018, "month": 1}, "value": 100.0}, {"date": {"year": 2018, "month": 2}, "value": 99.47036667901308}, {"date": {"year": 2018, "month": 3}, "value": 99.47036667901308}, {"date": {"year": 2018, "month": 4}, "value": 99.47036667901308}, {"date": {"year": 2018, "month": 5}, "value": 99.47036667901308}, {"date": {"year": 2018, "month": 6}, "value": 99.47036667901308}, {"date": {"year": 2018, "month": 7}, "value": 99.47036667901308}, {"date": {"year": 2018, "month": 8}, "value": 99.47036667901308}, {"date": {"year": 2018, "month": 9}, "value": 99.47036667901308}, {"date": {"year": 2018, "month": 10}, "value": 99.47036667901308}, {"date": {"year": 2018, "month": 11}, "value": 102.64816660493467}, {"date": {"year": 2018, "month": 12}, "value": 102.64816660493467}, {"date": {"year": 2019, "month": 1}, "value": 102.64816660493467}, {"date": {"year": 2019, "month": 2}, "value": 102.64816660493467}, {"date": {"year": 2019, "month": 3}, "value": 102.64816660493467}, {"date": {"year": 2019, "month": 4}, "value": 102.64816660493467}, {"date": {"year": 2019, "month": 5}, "value": 102.64816660493467}, {"date": {"year": 2019, "month": 6}, "value": 102.64816660493467}, {"date": {"year": 2019, "month": 7}, "value": 105.20489970349036}, {"date": {"year": 2019, "month": 8}, "value": 102.64816660493467}, {"date": {"year": 2019, "month": 9}, "value": 102.64816660493467}, {"date": {"year": 2019, "month": 10}, "value": 102.64816660493467}, {"date": {"year": 2019, "month": 11}, "value": 102.64816660493467}, {"date": {"year": 2019, "month": 12}, "value": 102.64816660493467}, {"date": {"year": 2020, "month": 1}, "value": 102.64816660493467}, {"date": {"year": 2020, "month": 2}, "value": 102.64816660493467}, {"date": {"year": 2020, "month": 3}, "value": 102.64816660493467}, {"date": {"year": 2020, "month": 4}, "value": 102.64816660493467}, {"date": {"year": 2020, "month": 5}, "value": 102.64816660493467}, {"date": {"year": 2020, "month": 6}, "value": 102.64816660493467}, {"date": {"year": 2020, "month": 7}, "value": 102.64816660493467}, {"date": {"year": 2020, "month": 8}, "value": 102.64816660493467}, {"date": {"year": 2020, "month": 9}, "value": 100.82083155332388}, {"date": {"year": 2020, "month": 10}, "value": 100.82083155332388}, {"date": {"year": 2020, "month": 11}, "value": 100.82083155332388}, {"date": {"year": 2020, "month": 12}, "value": 100.82083155332388}, {"date": {"year": 2021, "month": 1}, "value": 100.82083155332388}, {"date": {"year": 2021, "month": 2}, "value": 100.82083155332388}, {"date": {"year": 2021, "month": 3}, "value": 100.82083155332388}, {"date": {"year": 2021, "month": 4}, "value": 100.8593414913118}, {"date": {"year": 2021, "month": 5}, "value": 100.8593414913118}, {"date": {"year": 2021, "month": 6}, "value": 100.8593414913118}, {"date": {"year": 2021, "month": 7}, "value": 100.76425586364923}, {"date": {"year": 2021, "month": 8}, "value": 100.76425586364923}, {"date": {"year": 2021, "month": 9}, "value": 100.76425586364923}, {"date": {"year": 2021, "month": 10}, "value": 100.76425586364923}, {"date": {"year": 2021, "month": 11}, "value": 100.76425586364923}, {"date": {"year": 2021, "month": 12}, "value": 100.76425586364923}, {"date": {"year": 2022, "month": 1}, "value": 100.76425586364923}, {"date": {"year": 2022, "month": 2}, "value": 100.92244863307162}, {"date": {"year": 2022, "month": 3}, "value": 102.68808519352343}, {"date": {"year": 2022, "month": 4}, "value": 102.73422475127163}]}, {"name": "Restaurantes, Hot\u00e9is, Caf\u00e9s e Similares", "by": "by-product", "values": [{"date": {"year": 2018, "month": 1}, "value": 100.0}, {"date": {"year": 2018, "month": 2}, "value": 100.31776216203949}, {"date": {"year": 2018, "month": 3}, "value": 100.31776216203949}, {"date": {"year": 2018, "month": 4}, "value": 100.31776216203949}, {"date": {"year": 2018, "month": 5}, "value": 100.77907901640577}, {"date": {"year": 2018, "month": 6}, "value": 99.85443143812596}, {"date": {"year": 2018, "month": 7}, "value": 100.62329286206972}, {"date": {"year": 2018, "month": 8}, "value": 99.39647103300517}, {"date": {"year": 2018, "month": 9}, "value": 99.76171973461648}, {"date": {"year": 2018, "month": 10}, "value": 99.50859050546308}, {"date": {"year": 2018, "month": 11}, "value": 99.40268338107788}, {"date": {"year": 2018, "month": 12}, "value": 99.40268338107788}, {"date": {"year": 2019, "month": 1}, "value": 99.40268338107788}, {"date": {"year": 2019, "month": 2}, "value": 99.40268338107788}, {"date": {"year": 2019, "month": 3}, "value": 99.48677298542131}, {"date": {"year": 2019, "month": 4}, "value": 99.48677298542131}, {"date": {"year": 2019, "month": 5}, "value": 105.81945636590302}, {"date": {"year": 2019, "month": 6}, "value": 105.81945636590302}, {"date": {"year": 2019, "month": 7}, "value": 104.71136829038753}, {"date": {"year": 2019, "month": 8}, "value": 103.33497186563103}, {"date": {"year": 2019, "month": 9}, "value": 103.82367559359547}, {"date": {"year": 2019, "month": 10}, "value": 103.82367559359547}, {"date": {"year": 2019, "month": 11}, "value": 103.87078359203844}, {"date": {"year": 2019, "month": 12}, "value": 104.0165067813717}, {"date": {"year": 2020, "month": 1}, "value": 104.0165067813717}, {"date": {"year": 2020, "month": 2}, "value": 104.69464961066184}, {"date": {"year": 2020, "month": 3}, "value": 104.69464961066184}, {"date": {"year": 2020, "month": 4}, "value": 105.1877255651134}, {"date": {"year": 2020, "month": 5}, "value": 104.76940744297454}, {"date": {"year": 2020, "month": 6}, "value": 108.92344606886894}, {"date": {"year": 2020, "month": 7}, "value": 116.41434146743454}, {"date": {"year": 2020, "month": 8}, "value": 116.02906189002711}, {"date": {"year": 2020, "month": 9}, "value": 116.32330774202092}, {"date": {"year": 2020, "month": 10}, "value": 116.44792841804801}, {"date": {"year": 2020, "month": 11}, "value": 115.93215639904093}, {"date": {"year": 2020, "month": 12}, "value": 116.01744911855299}, {"date": {"year": 2021, "month": 1}, "value": 116.02199269868292}, {"date": {"year": 2021, "month": 2}, "value": 119.30681626172537}, {"date": {"year": 2021, "month": 3}, "value": 121.77575348401903}, {"date": {"year": 2021, "month": 4}, "value": 127.24390973072954}, {"date": {"year": 2021, "month": 5}, "value": 127.29293117031033}, {"date": {"year": 2021, "month": 6}, "value": 124.23775052040202}, {"date": {"year": 2021, "month": 7}, "value": 124.74460078206849}, {"date": {"year": 2021, "month": 8}, "value": 134.61024717733386}, {"date": {"year": 2021, "month": 9}, "value": 136.22852426181103}, {"date": {"year": 2021, "month": 10}, "value": 137.77409395607987}, {"date": {"year": 2021, "month": 11}, "value": 140.85007063532643}, {"date": {"year": 2021, "month": 12}, "value": 145.18361191547743}, {"date": {"year": 2022, "month": 1}, "value": 152.904507928378}, {"date": {"year": 2022, "month": 2}, "value": 151.96226692372784}, {"date": {"year": 2022, "month": 3}, "value": 150.43156708219183}, {"date": {"year": 2022, "month": 4}, "value": 153.8771746329186}]}, {"name": "Bens e Servi\u00e7os Diversos", "by": "by-product", "values": [{"date": {"year": 2018, "month": 1}, "value": 100.0}, {"date": {"year": 2018, "month": 2}, "value": 99.62888275353275}, {"date": {"year": 2018, "month": 3}, "value": 99.58042205132017}, {"date": {"year": 2018, "month": 4}, "value": 99.62324566245353}, {"date": {"year": 2018, "month": 5}, "value": 99.64807040252447}, {"date": {"year": 2018, "month": 6}, "value": 99.7720633891806}, {"date": {"year": 2018, "month": 7}, "value": 100.16155165962788}, {"date": {"year": 2018, "month": 8}, "value": 100.17705660324322}, {"date": {"year": 2018, "month": 9}, "value": 100.13692831940504}, {"date": {"year": 2018, "month": 10}, "value": 100.17705660324322}, {"date": {"year": 2018, "month": 11}, "value": 100.73291990096823}, {"date": {"year": 2018, "month": 12}, "value": 100.73291990096823}, {"date": {"year": 2019, "month": 1}, "value": 100.66098389387597}, {"date": {"year": 2019, "month": 2}, "value": 102.52942135209817}, {"date": {"year": 2019, "month": 3}, "value": 102.67673682518108}, {"date": {"year": 2019, "month": 4}, "value": 102.83535789209581}, {"date": {"year": 2019, "month": 5}, "value": 108.05845590033702}, {"date": {"year": 2019, "month": 6}, "value": 108.21827758964562}, {"date": {"year": 2019, "month": 7}, "value": 109.57182304249851}, {"date": {"year": 2019, "month": 8}, "value": 110.4061311000009}, {"date": {"year": 2019, "month": 9}, "value": 112.7596832533227}, {"date": {"year": 2019, "month": 10}, "value": 112.84598938749026}, {"date": {"year": 2019, "month": 11}, "value": 113.28884280251789}, {"date": {"year": 2019, "month": 12}, "value": 113.37413456749536}, {"date": {"year": 2020, "month": 1}, "value": 113.49981431909248}, {"date": {"year": 2020, "month": 2}, "value": 112.94258858494874}, {"date": {"year": 2020, "month": 3}, "value": 113.21590613047195}, {"date": {"year": 2020, "month": 4}, "value": 113.21590613047195}, {"date": {"year": 2020, "month": 5}, "value": 113.92548999272316}, {"date": {"year": 2020, "month": 6}, "value": 113.97022220259679}, {"date": {"year": 2020, "month": 7}, "value": 118.65361260216385}, {"date": {"year": 2020, "month": 8}, "value": 121.08587800280132}, {"date": {"year": 2020, "month": 9}, "value": 123.30962751063113}, {"date": {"year": 2020, "month": 10}, "value": 123.52749791354769}, {"date": {"year": 2020, "month": 11}, "value": 125.51909865380881}, {"date": {"year": 2020, "month": 12}, "value": 125.90873118126366}, {"date": {"year": 2021, "month": 1}, "value": 125.9190050563955}, {"date": {"year": 2021, "month": 2}, "value": 126.85507367564543}, {"date": {"year": 2021, "month": 3}, "value": 126.96997364318092}, {"date": {"year": 2021, "month": 4}, "value": 128.52992008242873}, {"date": {"year": 2021, "month": 5}, "value": 129.65515898757525}, {"date": {"year": 2021, "month": 6}, "value": 128.8952915763376}, {"date": {"year": 2021, "month": 7}, "value": 128.96421176554557}, {"date": {"year": 2021, "month": 8}, "value": 127.115753816183}, {"date": {"year": 2021, "month": 9}, "value": 127.11438899899127}, {"date": {"year": 2021, "month": 10}, "value": 127.71737306998739}, {"date": {"year": 2021, "month": 11}, "value": 128.44223130145448}, {"date": {"year": 2021, "month": 12}, "value": 128.9274786823479}, {"date": {"year": 2022, "month": 1}, "value": 130.13355795098397}, {"date": {"year": 2022, "month": 2}, "value": 130.32534528329677}, {"date": {"year": 2022, "month": 3}, "value": 130.15285329069567}, {"date": {"year": 2022, "month": 4}, "value": 130.71945851793083}]}]